net_task_client/__init__.py
net_task_client/config.yml
net_task_client/defaults.yml
net_task_client/groups.yml
net_task_client/hosts.yml
net_task_client-0.1.4.dist-info/licenses/LICENSE
net_task_client-0.1.4.dist-info/METADATA
net_task_client-0.1.4.dist-info/WHEEL
net_task_client-0.1.4.dist-info/top_level.txt
net_task_client-0.1.4.dist-info/RECORD
