Metadata-Version: 2.4
Name: net_task_client
Version: 0.1.4
Summary: A nornir net task project
Author-email: Larry Zhu <larry.lan.zhu@gmail.com>
License-Expression: MIT
Project-URL: Repository, https://github.com/myusernamehasbeentaken/net-task-client
Keywords: network,task,client
Classifier: Programming Language :: Python :: 3.9
Classifier: Operating System :: OS Independent
Requires-Python: >=3.9
License-File: LICENSE
Requires-Dist: nornir>=3.5.0
Requires-Dist: nornir_netmiko>=1.0.1
Requires-Dist: nornir_utils>=0.2.0
Dynamic: license-file
